mcp_runtime-0.1.4.dist-info/licenses/LICENSE
runtime/__init__.py
runtime/blueprint.py
runtime/client.py
runtime/errors.py
runtime/runtime.py
runtime/utils.py
runtime/adapter/__init__.py
runtime/adapter/base.py
runtime/adapter/claude.py
runtime/adapter/gemini.py
runtime/adapter/openai.py
runtime/discovery/__init__.py
runtime/discovery/discoverer.py
runtime/execution/__init__.py
runtime/execution/prompt_expander.py
runtime/execution/resource_resolver.py
runtime/execution/tool_executor.py
runtime/transport/__init__.py
runtime/transport/base.py
runtime/transport/http_sse.py
runtime/transport/stdio.py
schemas/__init__.py
schemas/mcp_types.py
mcp_runtime-0.1.4.dist-info/METADATA
mcp_runtime-0.1.4.dist-info/WHEEL
mcp_runtime-0.1.4.dist-info/top_level.txt
mcp_runtime-0.1.4.dist-info/RECORD
