Metadata-Version: 2.4
Name: mcp-runtime
Version: 0.1.4
Summary: Simple Python library to connect LLM models with MCP (Model Context Protocol) servers
Author: Aditya Jangam
Author-email: Aditya Jangam <adjangam9@gmail.com>
License: MIT
Project-URL: Homepage, https://github.com/Aaditya17032002/mcp-runtime
Project-URL: Documentation, https://github.com/Aaditya17032002/mcp-runtime#readme
Project-URL: Repository, https://github.com/Aaditya17032002/mcp-runtime
Project-URL: Issues, https://github.com/Aaditya17032002/mcp-runtime/issues
Keywords: mcp,model-context-protocol,llm,runtime
Classifier: Development Status :: 3 - Alpha
Classifier: Intended Audience :: Developers
Classifier: License :: OSI Approved :: MIT License
Classifier: Programming Language :: Python :: 3
Classifier: Programming Language :: Python :: 3.10
Classifier: Programming Language :: Python :: 3.11
Classifier: Programming Language :: Python :: 3.12
Requires-Python: >=3.10
License-File: LICENSE
Requires-Dist: jsonschema>=4.0.0
Requires-Dist: aiohttp>=3.8.0
Provides-Extra: dev
Requires-Dist: pytest>=7.0.0; extra == "dev"
Requires-Dist: pytest-asyncio>=0.21.0; extra == "dev"
Requires-Dist: black>=23.0.0; extra == "dev"
Requires-Dist: mypy>=1.0.0; extra == "dev"
Provides-Extra: openai
Requires-Dist: openai>=1.0.0; extra == "openai"
Provides-Extra: gemini
Requires-Dist: google-generativeai>=0.3.0; extra == "gemini"
Provides-Extra: claude
Requires-Dist: anthropic>=0.18.0; extra == "claude"
Dynamic: author
Dynamic: license-file
Dynamic: requires-python
